{
  "setting": {
    "urlCheck": true,
    "es6": true,
    "postcss": true,
    "minified": true,
    "newFeature": true,
    "autoCompile": true
  },
  "appid": "tt4e7b38c6d1458c5601",
  "projectname": "mypicture",
  "condition": {
    "miniprogram": {
      "current": 1654743704646,
      "list": [
        {
          "id": 1654743704646,
          "name": "pages/search/index",
          "pathName": "pages/index/index",
          "query": "",
          "scene": "990001",
          "launchFrom": "scan",
          "location": "qr_code"
        }
      ]
    }
  }
}
